Metadata-Version: 2.1
Name: twitter-auto-unfollow-bot
Version: 1.0.0
Summary: A python library to unfollow user on twitter automatically.
Home-page: https://twitter-api.datakund.com/en/latest/
Author: DataKund
Author-email: datakund@gmail.com
License: Apache License 2.0
Keywords: twitter python bot_studio automation login unfollow user
Platform: UNKNOWN
